Pyth3rNalisis/__init__.py
Pyth3rNalisis/__main__.py
Pyth3rNalisis/modules/__init__.py
Pyth3rNalisis/modules/module_banner.py
Pyth3rNalisis/modules/module_log.py
Pyth3rNalisis/modules/worker_CommandAndControl.py
Pyth3rNalisis/modules/worker_entropy.py
Pyth3rNalisis/modules/worker_extension.py
Pyth3rNalisis/modules/worker_hashingAnalisis.py
Pyth3rNalisis/modules/worker_metadata.py
Pyth3rNalisis-0.0.6.dist-info/LICENSE
Pyth3rNalisis-0.0.6.dist-info/METADATA
Pyth3rNalisis-0.0.6.dist-info/WHEEL
Pyth3rNalisis-0.0.6.dist-info/entry_points.txt
Pyth3rNalisis-0.0.6.dist-info/top_level.txt
Pyth3rNalisis-0.0.6.dist-info/RECORD
