Metadata-Version: 2.1
Name: Pyth3rNalisis
Version: 0.0.6
Summary: Pyth3rNalisis is a malware analysis tool that searches for red flags in any file.
Home-page: https://github.com/Pyth3rEx/Pyth3rNalisis
Author: Pyth3rEx
Classifier: Programming Language :: Python :: 3
Classifier: License :: OSI Approved :: GNU General Public License v3 (GPLv3)
Classifier: Operating System :: OS Independent
Classifier: Topic :: Security
Classifier: Natural Language :: English
Classifier: Intended Audience :: System Administrators
Classifier: Intended Audience :: Information Technology
Classifier: Development Status :: 3 - Alpha
Requires-Python: >=3.11
License-File: LICENSE
Requires-Dist: certifi >=2024.7.4
Requires-Dist: cffi >=1.17.0
Requires-Dist: charset-normalizer >=3.3.2
Requires-Dist: colorama >=0.4.6
Requires-Dist: colorclass >=2.2.2
Requires-Dist: cryptography >=43.0.0
Requires-Dist: easygui >=0.98.3
Requires-Dist: filetype >=1.2.0
Requires-Dist: idna >=3.7
Requires-Dist: lxml >=5.3.0
Requires-Dist: msoffcrypto-tool >=5.4.2
Requires-Dist: olefile >=0.47
Requires-Dist: oletools >=0.60.2
Requires-Dist: pcodedmp >=1.2.6
Requires-Dist: pefile >=2023.2.7
Requires-Dist: pycparser >=2.22
Requires-Dist: pyfiglet >=1.0.2
Requires-Dist: pyparsing >=3.1.2
Requires-Dist: PyPDF2 >=3.0.1
Requires-Dist: python-docx >=1.1.2
Requires-Dist: python-magic >=0.4.27
Requires-Dist: requests >=2.32.3
Requires-Dist: setuptools >=73.0.1
Requires-Dist: tabulate >=0.9.0
Requires-Dist: typing-extensions >=4.12.2
Requires-Dist: urllib3 >=2.2.2
Requires-Dist: win-unicode-console >=0.5
